dreamnet/__init__.py
dreamnet/dream.py
dreamnet/english_cnet.py
dreamnet/nounlist.txt
dreamnet/scene.py
dreamnet-1.2.dist-info/LICENSE
dreamnet-1.2.dist-info/METADATA
dreamnet-1.2.dist-info/WHEEL
dreamnet-1.2.dist-info/entry_points.txt
dreamnet-1.2.dist-info/top_level.txt
dreamnet-1.2.dist-info/RECORD
